scrapling/__init__.py
scrapling/cli.py
scrapling/defaults.py
scrapling/elements_storage.db
scrapling/fetchers.py
scrapling/parser.py
scrapling/py.typed
scrapling/core/__init__.py
scrapling/core/_types.py
scrapling/core/custom_types.py
scrapling/core/mixins.py
scrapling/core/storage_adaptors.py
scrapling/core/translator.py
scrapling/core/utils.py
scrapling/engines/__init__.py
scrapling/engines/camo.py
scrapling/engines/constants.py
scrapling/engines/pw.py
scrapling/engines/static.py
scrapling/engines/toolbelt/__init__.py
scrapling/engines/toolbelt/custom.py
scrapling/engines/toolbelt/fingerprints.py
scrapling/engines/toolbelt/navigation.py
scrapling/engines/toolbelt/bypasses/navigator_plugins.js
scrapling/engines/toolbelt/bypasses/notification_permission.js
scrapling/engines/toolbelt/bypasses/pdf_viewer.js
scrapling/engines/toolbelt/bypasses/playwright_fingerprint.js
scrapling/engines/toolbelt/bypasses/screen_props.js
scrapling/engines/toolbelt/bypasses/webdriver_fully.js
scrapling/engines/toolbelt/bypasses/window_chrome.js
scrapling_zhng-0.2.99.dist-info/licenses/LICENSE
tests/__init__.py
tests/fetchers/__init__.py
tests/fetchers/test_utils.py
tests/fetchers/async/__init__.py
tests/fetchers/async/test_camoufox.py
tests/fetchers/async/test_httpx.py
tests/fetchers/async/test_playwright.py
tests/fetchers/sync/__init__.py
tests/fetchers/sync/test_camoufox.py
tests/fetchers/sync/test_httpx.py
tests/fetchers/sync/test_playwright.py
tests/parser/__init__.py
tests/parser/test_automatch.py
tests/parser/test_general.py
scrapling_zhng-0.2.99.dist-info/METADATA
scrapling_zhng-0.2.99.dist-info/WHEEL
scrapling_zhng-0.2.99.dist-info/entry_points.txt
scrapling_zhng-0.2.99.dist-info/top_level.txt
scrapling_zhng-0.2.99.dist-info/RECORD
