Metadata-Version: 2.4
Name: scrapling-zhng
Version: 0.2.99
Summary: Scrapling is an undetectable, powerful, flexible, high-performance Python library that makes Web Scraping easy again! In an internet filled with complications,
Home-page: https://github.com/D4Vinci/Scrapling
Author: Karim Shoair
Author-email: karim.shoair@pm.me
License: BSD
Project-URL: Documentation, https://scrapling.readthedocs.io/en/latest/
Project-URL: Source, https://github.com/D4Vinci/Scrapling
Project-URL: Tracker, https://github.com/D4Vinci/Scrapling/issues
Classifier: Operating System :: OS Independent
Classifier: Development Status :: 4 - Beta
Classifier: Intended Audience :: Developers
Classifier: License :: OSI Approved :: BSD License
Classifier: Natural Language :: English
Classifier: Topic :: Internet :: WWW/HTTP
Classifier: Topic :: Text Processing :: Markup
Classifier: Topic :: Internet :: WWW/HTTP :: Browsers
Classifier: Topic :: Text Processing :: Markup :: HTML
Classifier: Topic :: Software Development :: Libraries :: Python Modules
Classifier: Programming Language :: Python :: 3
Classifier: Programming Language :: Python :: 3 :: Only
Classifier: Programming Language :: Python :: 3.9
Classifier: Programming Language :: Python :: 3.10
Classifier: Programming Language :: Python :: 3.11
Classifier: Programming Language :: Python :: 3.12
Classifier: Programming Language :: Python :: 3.13
Classifier: Programming Language :: Python :: Implementation :: CPython
Classifier: Typing :: Typed
Requires-Python: >=3.9
License-File: LICENSE
Requires-Dist: lxml>=5.0
Requires-Dist: cssselect>=1.2
Requires-Dist: click
Requires-Dist: w3lib
Requires-Dist: orjson>=3
Requires-Dist: tldextract
Requires-Dist: httpx[brotli,socks,zstd]
Requires-Dist: playwright>=1.49.1
Requires-Dist: rebrowser-playwright>=1.49.1
Requires-Dist: camoufox[geoip]>=0.4.11
Dynamic: author
Dynamic: author-email
Dynamic: classifier
Dynamic: description
Dynamic: description-content-type
Dynamic: home-page
Dynamic: license
Dynamic: license-file
Dynamic: project-url
Dynamic: requires-dist
Dynamic: requires-python
Dynamic: summary
